sql_query_anonymizer/__init__.py
sql_query_anonymizer/anonymize.py
sql_query_anonymizer/cli.py
sql_query_anonymizer/constants.py
sql_query_anonymizer/helper_utilities.py
sql_query_anonymizer/tokenize.py
sql_query_anonymizer/utils.py
sql_query_anonymizer-0.1.2.dist-info/WHEEL
sql_query_anonymizer-0.1.2.dist-info/entry_points.txt
sql_query_anonymizer-0.1.2.dist-info/METADATA
sql_query_anonymizer-0.1.2.dist-info/RECORD
