Metadata-Version: 2.3
Name: sql-query-anonymizer
Version: 0.1.2
Summary: Tool for anonymizing schema data in SQL queries.
Author: Nicholas Carsner
Author-email: Nicholas Carsner <nicholascarsner@gmail.com>
Requires-Python: >=3.13
